featselectlib/__init__.py
featselectlib/supervised_feature_selection/Lspin.py
featselectlib/supervised_feature_selection/__init__.py
featselectlib/supervised_feature_selection/stg/__init__.py
featselectlib/supervised_feature_selection/stg/python/__init__.py
featselectlib/supervised_feature_selection/stg/python/setup.py
featselectlib/supervised_feature_selection/stg/python/stg/__init__.py
featselectlib/supervised_feature_selection/stg/python/stg/io.py
featselectlib/supervised_feature_selection/stg/python/stg/layers.py
featselectlib/supervised_feature_selection/stg/python/stg/losses.py
featselectlib/supervised_feature_selection/stg/python/stg/matching.py
featselectlib/supervised_feature_selection/stg/python/stg/meter.py
featselectlib/supervised_feature_selection/stg/python/stg/models.py
featselectlib/supervised_feature_selection/stg/python/stg/stg.py
featselectlib/supervised_feature_selection/stg/python/stg/utils.py
featselectlib/supervised_feature_selection/stg/python/stg/datasets/__init__.py
featselectlib/unsupervised_feature_selection/__init__.py
featselectlib/unsupervised_feature_selection/setup.py
featselectlib/unsupervised_feature_selection/src/__init__.py
featselectlib/unsupervised_feature_selection/src/lscae/__init__.py
featselectlib/unsupervised_feature_selection/src/lscae/experiments.py
featselectlib/unsupervised_feature_selection/src/lscae/gated_laplacian.py
featselectlib-0.1.0.dist-info/METADATA
featselectlib-0.1.0.dist-info/WHEEL
featselectlib-0.1.0.dist-info/top_level.txt
featselectlib-0.1.0.dist-info/RECORD
