Metadata-Version: 2.1
Name: featselectlib
Version: 0.1.0
Summary: A library combining different feature selection methods
Home-page: https://github.com/LindenbaumLab/project-featselectlib
Author: LindenbaumLab
Author-email: your.email@example.com
Classifier: Programming Language :: Python :: 3
Classifier: License :: OSI Approved :: MIT License
Classifier: Operating System :: OS Independent
Requires-Python: >=3.6
Requires-Dist: torch
Requires-Dist: scikit-learn
Requires-Dist: omegaconf
Requires-Dist: scipy
Requires-Dist: matplotlib
